CHANGES.txt
COPYRIGHT.txt
LICENSE.txt
README.txt
setup.py
docs/Makefile
docs/conf.py
docs/index.rst
docs/.static/logo_hi.gif
docs/.static/repoze.css
repoze/__init__.py
repoze.depinj.egg-info/PKG-INFO
repoze.depinj.egg-info/SOURCES.txt
repoze.depinj.egg-info/dependency_links.txt
repoze.depinj.egg-info/entry_points.txt
repoze.depinj.egg-info/namespace_packages.txt
repoze.depinj.egg-info/not-zip-safe
repoze.depinj.egg-info/top_level.txt
repoze/depinj/__init__.py
repoze/depinj/tests.py