Metadata-Version: 1.0
Name: repoze.depinj
Version: 0.2
Summary: Small dependency injection framework for unit testing
Home-page: http://www.repoze.org
Author: Agendaless Consulting
Author-email: repoze-dev@lists.repoze.org
License: BSD-derived (http://www.repoze.org/LICENSE.txt)
Keywords: dependency injection unit testing
Platform: UNKNOWN
Classifier: Intended Audience :: Developers
Classifier: Programming Language :: Python
